babelone-0.1.9.dist-info/METADATA
babelone-0.1.9.dist-info/WHEEL
babelone-0.1.9.dist-info/entry_points.txt
babelone-0.1.9.dist-info/license_files/LICENSE
babelone_cli/__init__.py
babelone_cli/main.py
babelone_cli/_babelone_core.cpython-311-i386-linux-gnu.so
babelone-0.1.9.dist-info/RECORD
