Metadata-Version: 2.3
Name: babelone
Version: 0.1.9
Classifier: Programming Language :: Rust
Classifier: Programming Language :: Python :: Implementation :: CPython
Classifier: Programming Language :: Python :: Implementation :: PyPy
Requires-Dist: rich-click
License-File: LICENSE
Summary: CLI for scaffolding and translating Python build spec files.
Keywords: rust,pyo3,rustpython,cli
Author-email: "Rahul D. Ghosal" <rdghosal@gmail.com>
Maintainer-email: "Rahul D. Ghosal" <rdghosal@gmail.com>
License: MIT License
Requires-Python: >=3.8
Project-URL: repository, https://github.com/rdghosal/babelone
